markettracker/__init__.py
markettracker/admin.py
markettracker/app_settings.py
markettracker/apps.py
markettracker/auth_hooks.py
markettracker/discord.py
markettracker/esi.py
markettracker/forms.py
markettracker/models.py
markettracker/tasks.py
markettracker/urls.py
markettracker/utils.py
markettracker/views.py
markettracker/locale/.gitkeep
markettracker/management/commands/cleanup_deliveries.py
markettracker/migrations/0001_initial.py
markettracker/migrations/0002_discordmessage_and_more.py
markettracker/migrations/0003_marketordersnapshot.py
markettracker/migrations/0004_trackedcontract_last_status.py
markettracker/migrations/0005_seed_default_tracking_config.py
markettracker/migrations/0006_discordmessage_item_restocked_alert_header_and_more.py
markettracker/migrations/0007_contractsnapshot_date_completed.py
markettracker/migrations/0008_mttasklog.py
markettracker/migrations/0009_alter_mttasklog_options.py
markettracker/migrations/0010_discordmessage_contract_restocked_alert_header_and_more.py
markettracker/migrations/__init__.py
markettracker/static/markettracker/.gitkeep
markettracker/static/markettracker/js/hide_fields.js
markettracker/templates/markettracker/admin_deliveries.html
markettracker/templates/markettracker/base.html
markettracker/templates/markettracker/contract_delivery_form.html
markettracker/templates/markettracker/contracts_list.html
markettracker/templates/markettracker/deliveries_list.html
markettracker/templates/markettracker/delivery_form.html
markettracker/templates/markettracker/diagnostics.html
markettracker/templates/markettracker/item_detail.html
markettracker/templates/markettracker/list_items.html
markettracker/templates/markettracker/manage_stock.html
markettracker/templatetags/__init__.py
markettracker/templatetags/market_extras.py
markettracker/tests/__init__.py
markettracker/tests/test_example.py
markettracker/tests/test_tasks.py
aa_markettracker_plugin-1.3.4.dist-info/METADATA
aa_markettracker_plugin-1.3.4.dist-info/WHEEL
aa_markettracker_plugin-1.3.4.dist-info/licenses/LICENSE
aa_markettracker_plugin-1.3.4.dist-info/RECORD
