Metadata-Version: 2.4
Name: aa-markettracker-plugin
Version: 1.3.4
Summary: Market tracking module for allianceauth
Author-email: Peter Pfeufer <develop@ppfeufer.de>
License:                     GNU GENERAL PUBLIC LICENSE
License-File: LICENSE
Keywords: allianceauth,markettracker
Classifier: Environment :: Web Environment
Classifier: Framework :: Django
Classifier: Framework :: Django :: 4.2
Classifier: Intended Audience :: Developers
Classifier: License :: OSI Approved :: GNU General Public License v3 (GPLv3)
Classifier: Operating System :: OS Independent
Classifier: Programming Language :: Python
Classifier: Programming Language :: Python :: 3 :: Only
Classifier: Programming Language :: Python :: 3.10
Classifier: Programming Language :: Python :: 3.11
Classifier: Programming Language :: Python :: 3.12
Classifier: Programming Language :: Python :: 3.13
Classifier: Topic :: Internet :: WWW/HTTP
Classifier: Topic :: Internet :: WWW/HTTP :: Dynamic Content
Requires-Python: >=3.10
